sqscraper/__init__.py
sqscraper/__main__.py
sqscraper/utils.py
sqscraper/cnbc/__init__.py
sqscraper/cnbc/_apps.py
sqscraper/cnbc/_serializer.py
sqscraper/cnbc/charts.py
sqscraper/cnbc/earnings.py
sqscraper/cnbc/quote_page.py
sqscraper/cnbc/summary.py
sqscraper-0.6.0.dist-info/LICENSE
sqscraper-0.6.0.dist-info/METADATA
sqscraper-0.6.0.dist-info/WHEEL
sqscraper-0.6.0.dist-info/top_level.txt
sqscraper-0.6.0.dist-info/RECORD
